pipen_cli_gbatch/__init__.py
pipen_cli_gbatch/daemon_args.toml
pipen_cli_gbatch-1.1.2.dist-info/METADATA
pipen_cli_gbatch-1.1.2.dist-info/WHEEL
pipen_cli_gbatch-1.1.2.dist-info/entry_points.txt
pipen_cli_gbatch-1.1.2.dist-info/RECORD
