Metadata-Version: 2.4
Name: pipen-cli-gbatch
Version: 1.1.2
Summary: A pipen cli plugin to run command via Google Cloud Batch
License: MIT
Author: pwwang
Author-email: pwwang@pwwang.com
Requires-Python: >=3.9,<4.0
Classifier: License :: OSI Approved :: MIT License
Classifier: Programming Language :: Python :: 3
Classifier: Programming Language :: Python :: 3.9
Classifier: Programming Language :: Python :: 3.10
Classifier: Programming Language :: Python :: 3.11
Classifier: Programming Language :: Python :: 3.12
Classifier: Programming Language :: Python :: 3.13
Classifier: Programming Language :: Python :: 3.14
Requires-Dist: panpath[async-gs] (>=0.4.9,<0.5.0)
Requires-Dist: pipen (>=1.1.2,<2.0.0)
Requires-Dist: pipen-poplog (>=1.1,<2.0)
Project-URL: Homepage, https://github.com/pwwang/pipen-cli-gbatch
Project-URL: Repository, https://github.com/pwwang/pipen-cli-gbatch
